MANIFEST.in
README.md
setup.cfg
setup.py
anthill/game/__init__.py
anthill/game/controller/__init__.py
anthill/game/controller/options.py
anthill/game/controller/server.py
anthill/game/controller/model/__init__.py
anthill/game/controller/model/controller.py
anthill/game/controller/model/debug.py
anthill/game/controller/model/delivery.py
anthill/game/controller/model/gameserver.py
anthill/game/controller/model/heartbeat.py
anthill/game/controller/model/master.py
anthill/game/controller/model/msg.py
anthill_game_controller.egg-info/PKG-INFO
anthill_game_controller.egg-info/SOURCES.txt
anthill_game_controller.egg-info/dependency_links.txt
anthill_game_controller.egg-info/namespace_packages.txt
anthill_game_controller.egg-info/not-zip-safe
anthill_game_controller.egg-info/requires.txt
anthill_game_controller.egg-info/top_level.txt