Metadata-Version: 1.0
Name: anthill-game-controller
Version: 0.2.8
Summary: Game servers hosting & matchmaking service for Anthill platform Edit Add topics
Home-page: https://github.com/anthill-platform/anthill-game-controller
Author: desertkun
Author-email: desertkun@gmail.com
License: MIT
Platform: UNKNOWN
